<HologicHeader1>
<Institution>
<Name>Desert Imaging Services LP-Lee Trevino</Name>
<StreetAddress>1727 N Lee Trevino</StreetAddress>
<CityAddress>El Paso, TX 79936</CityAddress>
<Phone>915-577-0100</Phone>
<Fax>915-577-9444</Fax>
<Email>raul@dielp.com</Email>
</Institution>
<GeneralData>
<ScanID>A0122260J</ScanID>
<ReportType> 1</ReportType>
<RegionForPlot> 17</RegionForPlot>
<Range> 0</Range>
<ROI> 0</ROI>
<RefCurveID> 155</RefCurveID>
<k> 1.138383</k>
<d0> 51.999475</d0>
<Thickness> 6.715153</Thickness>
<ROIWidth> 119</ROIWidth>
<ROIHeight> 111</ROIHeight>
<ImageXSize> 252</ImageXSize>
<ImageYSize> 320</ImageYSize>
<GraphXSize> 359</GraphXSize>
<GraphYSize> 320</GraphYSize>
<ImageXPos> 416</ImageXPos>
<ImageYPos> 180</ImageYPos>
<GraphXPos> 680</GraphXPos>
<GraphYPos> 180</GraphYPos>
<HL71Name></HL71Name>
<HL71Value></HL71Value>
<HL72Name></HL72Name>
<HL72Value></HL72Value>
<HL73Name></HL73Name>
<HL73Value></HL73Value>
<ImagePro></ImagePro>
<DAP>DAP: 1.7 cGy*cm<sup><small>2</small></sup></DAP>
</GeneralData>
</HologicHeader1>
<JavaScriptFile, filetype=1, filename="C:\QDR\qdrdicom\html2\PatInfo.js">
/ Filename = C:\QDR\qdrdicom\html2\PatInfo.js
// Written By HologicDICOMControl
PatientTitle = "Patient Information:";
PatientName = "JAQUEZ, BARBARA";
SSN = " ";
PatientID = "1032207";
PostalCode = " ";
PatientSex = "Female";
Ethnicity = "Hispanic";
Height = "60.0 in";
Weight = "160.0  lb";
DOB = "07/21/1945";
Age = "80";
MenopauseAge = "62";
ReferringPhysician = "KATHERINE, ARANDA";
</JavaScriptFile>
<JavaScriptFile, filetype=2, filename="C:\QDR\qdrdicom\html2\ScanInfo.js">
/ Filename = C:\QDR\qdrdicom\html2\ScanInfo.js
// Written By HologicDICOMControl
ScanTitle = "Scan Information:";
Scan = "January 22, 2026 - A0122260J";
ScanMode = "f Left Hip";
AnalDate = "01/22/2026 13:08";
AnalProtocol = "Hip";
Institution = "Desert Imaging Services LP-Lee Trevino";
Operator = "MA";
Model = "Horizon Ci (S/N303693M)";
Comment = " ";
ReportDate = "01/22/2026 13:12";
HologicSoftwareVer = "13.6.0.7";
</JavaScriptFile>
<JavaScriptFile, filetype=6, filename="C:\QDR\qdrdicom\html2\PComment.js">
/ Filename = C:\QDR\qdrdicom\html2\PComment.js
// Written By HologicDICOMControl
PhysicianComment = "All treatment decisions require clinical judgment and consideration of individual patient factors, including patient preferences, comorbidities, previous drug use and risk factors not captured in the FRAX model (e.g. frailty, falls, vitamin D deficiency, increased bone turnover, interval significant decline in BMD).";
</JavaScriptFile>
<JavaScriptFile, filetype=3, filename="C:\QDR\qdrdicom\html2\Results.js">
/ Filename = C:\QDR\qdrdicom\html2\Results.js
// Written By HologicDICOMControl
IncludeTable1 = true;
MAXROWS1 = 3;
MAXCOLS1 = 8;
TableTitle1 = "Results Summary:";
TableType1 = 1;
TableNote1 = "Total BMD CV 1.0%, ACF = 1.035, BCF = 1.022, TH = 6.715";
TableRowTypes1[ 0] = 1;
TableColumnTypes1[ 0] = 1;
ResultsTable1[ 0][ 0] = "Region";
TableColumnTypes1[ 1] = 2;
ResultsTable1[ 0][ 1] = "Area[cm<sup><small>2</small></sup>]";
TableColumnTypes1[ 2] = 4;
ResultsTable1[ 0][ 2] = "BMC[(g)]";
TableColumnTypes1[ 3] = 3;
ResultsTable1[ 0][ 3] = "BMD[g/cm<sup><small>2</small></sup>]";
TableColumnTypes1[ 4] = 5;
ResultsTable1[ 0][ 4] = "T-score";
TableColumnTypes1[ 5] = 7;
ResultsTable1[ 0][ 5] = "PR (Peak Reference)";
TableColumnTypes1[ 6] = 6;
ResultsTable1[ 0][ 6] = "Z-score";
TableColumnTypes1[ 7] = 13;
ResultsTable1[ 0][ 7] = "AM (Age Matched)";
TableRowTypes1[ 1] = 10;
TableColumnTypes1[ 0] = 1;
ResultsTable1[ 1][ 0] = "Neck";
TableColumnTypes1[ 1] = 2;
ResultsTable1[ 1][ 1] = "4.74";
TableColumnTypes1[ 2] = 4;
ResultsTable1[ 1][ 2] = "2.44";
TableColumnTypes1[ 3] = 3;
ResultsTable1[ 1][ 3] = "0.515";
TableColumnTypes1[ 4] = 5;
ResultsTable1[ 1][ 4] = "-3.0";
TableColumnTypes1[ 5] = 7;
ResultsTable1[ 1][ 5] = "59";
TableColumnTypes1[ 6] = 6;
ResultsTable1[ 1][ 6] = "-0.7";
TableColumnTypes1[ 7] = 13;
ResultsTable1[ 1][ 7] = "85";
TableRowTypes1[ 2] = 3;
TableColumnTypes1[ 0] = 1;
ResultsTable1[ 2][ 0] = "Total";
TableColumnTypes1[ 1] = 2;
ResultsTable1[ 2][ 1] = "34.21";
TableColumnTypes1[ 2] = 4;
ResultsTable1[ 2][ 2] = "26.30";
TableColumnTypes1[ 3] = 3;
ResultsTable1[ 2][ 3] = "0.769";
TableColumnTypes1[ 4] = 5;
ResultsTable1[ 2][ 4] = "-1.4";
TableColumnTypes1[ 5] = 7;
ResultsTable1[ 2][ 5] = "80";
TableColumnTypes1[ 6] = 6;
ResultsTable1[ 2][ 6] = "0.6";
TableColumnTypes1[ 7] = 13;
ResultsTable1[ 2][ 7] = "112";
IncludeTable2 = true;
MAXROWS2 = 3;
MAXCOLS2 = 6;
TableTitle2 = "Results History:";
TableType2 = 2;
TableNote2 = " ";
TableRowTypes2[ 0] = 1;
TableColumnTypes2[ 0] = 16;
ResultsTable2[ 0][ 0] = "Scan Date";
TableColumnTypes2[ 1] = 17;
ResultsTable2[ 0][ 1] = "Age";
TableColumnTypes2[ 2] = 3;
ResultsTable2[ 0][ 2] = "BMD";
TableColumnTypes2[ 3] = 5;
ResultsTable2[ 0][ 3] = "T-score";
TableColumnTypes2[ 4] = 18;
ResultsTable2[ 0][ 4] = "BMD Change vs Baseline";
TableColumnTypes2[ 5] = 19;
ResultsTable2[ 0][ 5] = "BMD Change vs Previous";
TableRowTypes2[ 1] = 4;
TableColumnTypes2[ 0] = 16;
ResultsTable2[ 1][ 0] = "01/22/2026";
TableColumnTypes2[ 1] = 17;
ResultsTable2[ 1][ 1] = "80";
TableColumnTypes2[ 2] = 3;
ResultsTable2[ 1][ 2] = "0.769";
TableColumnTypes2[ 3] = 5;
ResultsTable2[ 1][ 3] = "-1.4";
TableColumnTypes2[ 4] = 18;
ResultsTable2[ 1][ 4] = "4.0%*";
TableColumnTypes2[ 5] = 19;
ResultsTable2[ 1][ 5] = "4.0%*";
TableRowTypes2[ 2] = 4;
TableColumnTypes2[ 0] = 16;
ResultsTable2[ 2][ 0] = "01/09/2023";
TableColumnTypes2[ 1] = 17;
ResultsTable2[ 2][ 1] = "77";
TableColumnTypes2[ 2] = 3;
ResultsTable2[ 2][ 2] = "0.739";
TableColumnTypes2[ 3] = 5;
ResultsTable2[ 2][ 3] = "-1.7";
TableColumnTypes2[ 4] = 18;
ResultsTable2[ 2][ 4] = " ";
TableColumnTypes2[ 5] = 19;
ResultsTable2[ 2][ 5] = " ";
IncludeTable3 = true;
MAXROWS3 = 5;
MAXCOLS3 = 3;
TableTitle3 = "10-year Fracture Risk¹";
TableType3 = 8;
TableNote3 = "¹ FRAX® Version 3.08. Fracture probability calculated for an untreated patient. Fracture probability may be lower if the patient has received treatment.";
TableRowTypes3[ 0] = 1;
TableColumnTypes3[ 0] = 20;
ResultsTable3[ 0][ 0] = "10-year Fracture Risk¹";
TableColumnTypes3[ 1] = 32;
ResultsTable3[ 0][ 1] = " ";
TableColumnTypes3[ 2] = 33;
ResultsTable3[ 0][ 2] = " ";
TableRowTypes3[ 1] = 71;
TableColumnTypes3[ 0] = 20;
ResultsTable3[ 1][ 0] = "Major Osteoporotic Fracture";
TableColumnTypes3[ 1] = 32;
ResultsTable3[ 1][ 1] = "14%";
TableColumnTypes3[ 2] = 33;
ResultsTable3[ 1][ 2] = "20%";
TableRowTypes3[ 2] = 72;
TableColumnTypes3[ 0] = 20;
ResultsTable3[ 2][ 0] = "Hip Fracture";
TableColumnTypes3[ 1] = 32;
ResultsTable3[ 2][ 1] = "5.3%";
TableColumnTypes3[ 2] = 33;
ResultsTable3[ 2][ 2] = "6.9%";
TableRowTypes3[ 3] = 112;
TableColumnTypes3[ 0] = 20;
ResultsTable3[ 3][ 0] = "Reported Risk Factors:";
TableColumnTypes3[ 1] = 32;
ResultsTable3[ 3][ 1] = " ";
TableColumnTypes3[ 2] = 33;
ResultsTable3[ 3][ 2] = " ";
TableRowTypes3[ 4] = 73;
TableColumnTypes3[ 0] = 20;
ResultsTable3[ 4][ 0] = "US (Hispanic), T-score(WHO)=-2.9, BMI=31.2";
TableColumnTypes3[ 1] = 32;
ResultsTable3[ 4][ 1] = " ";
TableColumnTypes3[ 2] = 33;
ResultsTable3[ 4][ 2] = " ";
</JavaScriptFile>
<JavaScriptFile, filetype=4, filename="C:\QDR\qdrdicom\html2\Image.js">
/ Filename = C:\QDR\qdrdicom\html2\Image.js
// Written By HologicDICOMControl
ImageTitle1 = "Image not for diagnostic use";
ImageTitle2 = "119 x 111";
ImageTitle3 = "NECK: 49 x 15";
ImageTitle5 = "k = 1.138, d0 = 52.0";
ImageTitle6 = "DAP: 1.7 cGy*cm<sup><small>2</small></sup>";
</JavaScriptFile>
<JavaScriptFile, filetype=5, filename="C:\QDR\qdrdicom\html2\Graph.js">
/ Filename = C:\QDR\qdrdicom\html2\Graph.js
// Written By HologicDICOMControl
GraphTitle2 = "T-score vs. Hispanic Female. Source:NHANES<br> Z-score vs. Hispanic Female. Source:NHANES";
</JavaScriptFile>
<JavaScriptFile, filetype=7, filename="C:\QDR\qdrdicom\html2\Fracture.js">
/ Filename = C:\QDR\qdrdicom\html2\Fracture.js
// Written By HologicDICOMControl
FractureRiskStr = "WHO Classification: Osteoporosis<BR>* Denotes significance at 95% confidence level, LSC is 0.027 g/cm²";
</JavaScriptFile>
 